.pydistutils.cfg
MANIFEST.in
files.txt
requirements.txt
setup.py
topotb/__init__.py
topotb/irreptable.cpython-37m-x86_64-linux-gnu.so
topotb/phonon_lib.cpython-37m-x86_64-linux-gnu.so
topotb/phonon_util.cpython-37m-x86_64-linux-gnu.so
topotb/plot_band_tb.cpython-37m-x86_64-linux-gnu.so
topotb/print_version.cpython-37m-x86_64-linux-gnu.so
topotb/site_symmetry.cpython-37m-x86_64-linux-gnu.so
topotb/spinor.cpython-37m-x86_64-linux-gnu.so
topotb/structure.cpython-37m-x86_64-linux-gnu.so
topotb/topotb_help.cpython-37m-x86_64-linux-gnu.so
topotb/util.cpython-37m-x86_64-linux-gnu.so
topotb/version.cpython-37m-x86_64-linux-gnu.so
topotb.egg-info/PKG-INFO
topotb.egg-info/SOURCES.txt
topotb.egg-info/dependency_links.txt
topotb.egg-info/requires.txt
topotb.egg-info/top_level.txt
topotb/examples_electron/graphene/KMmodel.py
topotb/examples_electron/graphene/POSCAR
topotb/examples_electron/graphene/all_irreps.yaml
topotb/examples_electron/graphene/example1_graphene.py
topotb/examples_electron/graphene/graphene.cif
topotb/examples_electron/graphene/graphenekm.cif
topotb/examples_electron/graphene/graphenekm_standardized.cif
topotb/examples_electron/graphene/graphenen_band.pdf
topotb/examples_electron/graphene/irreps.yaml
topotb/examples_electron/graphene/kaka.jpeg
topotb/examples_electron/graphene/test_plot_str.py
topotb/examples_phonon/C7N3/FORCE_CONSTANTS_SPG
topotb/examples_phonon/C7N3/POSCAR
topotb/examples_phonon/C7N3/SPOSCAR
topotb/examples_phonon/C7N3/all_irreps.yaml
topotb/examples_phonon/C7N3/irreps.yaml
topotb/examples_phonon/C7N3/kaka.jpeg
topotb/examples_phonon/C7N3/ph_frequecny_C7N3.dat
topotb/examples_phonon/C7N3/ph_frequecny_C7N3_projected.dat
topotb/examples_phonon/C7N3/phon_C7N3.py
topotb/examples_phonon/CrI3/FORCE_CONSTANTS
topotb/examples_phonon/CrI3/POSCAR
topotb/examples_phonon/CrI3/SPOSCAR
topotb/examples_phonon/CrI3/all_irreps.yaml
topotb/examples_phonon/CrI3/irreps.yaml
topotb/examples_phonon/CrI3/kaka.jpeg
topotb/examples_phonon/CrI3/ph_frequecny_CrI3.dat
topotb/examples_phonon/CrI3/ph_frequecny_CrI3_projected.dat
topotb/examples_phonon/CrI3/phon_CrI3.py
