Metadata-Version: 1.0
Name: topotb
Version: 0.0.1
Summary: a tool to get symmetry proberties of wavefunction for electrons and phonon from tight-binding model
Home-page: UNKNOWN
Author: Pan Zhou, Lizhong Sun
Author-email: zhoupan71234@xtu.edu.cn
License: MIT License
Platform: UNKNOWN
